sawalni/__init__.py
sawalni/main.py
sawalni-0.2.11.dist-info/METADATA
sawalni-0.2.11.dist-info/WHEEL
sawalni-0.2.11.dist-info/top_level.txt
sawalni-0.2.11.dist-info/RECORD
