Metadata-Version: 2.1
Name: sawalni
Version: 0.2.11
Summary: Official Python SDK for the Sawalni API
Author: Omar Kamali
Author-email: api@sawalni.com
Keywords: nlp language processing embedding translation transliteration identification api sdk moroccan darija arabic multilingual low-resource languages
Classifier: Development Status :: 3 - Alpha
Classifier: Intended Audience :: Developers
Classifier: Programming Language :: Python :: 3
Classifier: Programming Language :: Python :: 3.7
Classifier: Programming Language :: Python :: 3.8
Classifier: Programming Language :: Python :: 3.9
Classifier: Programming Language :: Python :: 3.10
Classifier: Operating System :: OS Independent
Classifier: Topic :: Software Development :: Libraries :: Python Modules
Classifier: Topic :: Text Processing :: Linguistic
Requires-Python: >=3.7
Requires-Dist: requests
Requires-Dist: aiohttp
Requires-Dist: openai
Requires-Dist: tenacity
